sheesh/__init__.py
sheesh/app.py
sheesh/crypt/crypt.py
sheesh/crypt/crypto_utils.py
sheesh/general/__init__.py
sheesh/general/general.py
sheesh/general/text_utils.py
sheesh/main.py
sheesh-0.0.2.dist-info/LICENSE
sheesh-0.0.2.dist-info/METADATA
sheesh-0.0.2.dist-info/WHEEL
sheesh-0.0.2.dist-info/entry_points.txt
sheesh-0.0.2.dist-info/RECORD
